<?xml version="1.0" encoding="UTF-8"?><?xml-stylesheet type='text/xsl' href='_UpgradeReport_Files/UpgradeReport.xslt'?><UpgradeLog>
<Properties><Property Name="Solution" Value="HoseSlave">
</Property><Property Name="Solution File" Value="D:\MyDevelop\Projects\HoseSlave\Visual Studio\HoseSlave\HoseSlave.sln">
</Property><Property Name="Date" Value="2009. február 3.">
</Property><Property Name="Time" Value="9:41">
</Property></Properties><Event ErrorLevel="0" Project="" Source="HoseSlave.sln" Description="Solution converted successfully">
</Event><Event ErrorLevel="3" Project="" Source="HoseSlave.sln" Description="Converted">
</Event></UpgradeLog>